{
  "main": {
    "id": "2066232782be0a44",
    "type": "split",
    "children": [
      {
        "id": "25c70b95c19209ea",
        "type": "tabs",
        "children": [
          {
            "id": "a1a78276fe017888",
            "type": "leaf",
            "state": {
              "type": "markdown",
              "state": {
                "file": "代码随想录-算法训练营/day39_动态规划_part07/【动态规划】【树上dp】打家劫舍 III.md",
                "mode": "source",
                "source": false
              },
              "icon": "lucide-file",
              "title": "【动态规划】【树上dp】打家劫舍 III"
            }
          }
        ]
      }
    ],
    "direction": "vertical"
  },
  "left": {
    "id": "1a898bd6d9165ad9",
    "type": "split",
    "children": [
      {
        "id": "190119752ecc2059",
        "type": "tabs",
        "children": [
          {
            "id": "7529420d85d03519",
            "type": "leaf",
            "state": {
              "type": "file-explorer",
              "state": {
                "sortOrder": "alphabetical",
                "autoReveal": true
              },
              "icon": "lucide-folder-closed",
              "title": "文件列表"
            }
          },
          {
            "id": "035af9ab1c7c6356",
            "type": "leaf",
            "state": {
              "type": "search",
              "state": {
                "query": "",
                "matchingCase": false,
                "explainSearch": false,
                "collapseAll": false,
                "extraContext": false,
                "sortOrder": "alphabetical"
              },
              "icon": "lucide-search",
              "title": "搜索"
            }
          },
          {
            "id": "fd12158dc597f500",
            "type": "leaf",
            "state": {
              "type": "bookmarks",
              "state": {},
              "icon": "lucide-bookmark",
              "title": "书签"
            }
          }
        ]
      }
    ],
    "direction": "horizontal",
    "width": 359.5
  },
  "right": {
    "id": "354e1b9281dd2379",
    "type": "split",
    "children": [
      {
        "id": "4b11777f4748e495",
        "type": "tabs",
        "children": [
          {
            "id": "2f6ed5ffa20732c2",
            "type": "leaf",
            "state": {
              "type": "backlink",
              "state": {
                "file": "代码随想录-算法训练营/day22_回溯_part01/【回溯】【组合】电话号码的字母组合.md",
                "collapseAll": true,
                "extraContext": false,
                "sortOrder": "alphabetical",
                "showSearch": false,
                "searchQuery": "",
                "backlinkCollapsed": false,
                "unlinkedCollapsed": true
              },
              "icon": "links-coming-in",
              "title": "【回溯】【组合】电话号码的字母组合 的反向链接列表"
            }
          },
          {
            "id": "f57aa462c1fe7dba",
            "type": "leaf",
            "state": {
              "type": "outgoing-link",
              "state": {
                "file": "欢迎.md",
                "linksCollapsed": false,
                "unlinkedCollapsed": true
              },
              "icon": "links-going-out",
              "title": "欢迎 的出链列表"
            }
          },
          {
            "id": "04c96aab823bc982",
            "type": "leaf",
            "state": {
              "type": "tag",
              "state": {
                "sortOrder": "frequency",
                "useHierarchy": true,
                "showSearch": false,
                "searchQuery": ""
              },
              "icon": "lucide-tags",
              "title": "标签"
            }
          },
          {
            "id": "787c83aca619836f",
            "type": "leaf",
            "state": {
              "type": "all-properties",
              "state": {
                "sortOrder": "frequency",
                "showSearch": false,
                "searchQuery": ""
              },
              "icon": "lucide-archive",
              "title": "添加笔记属性"
            }
          },
          {
            "id": "e00946637d9323a1",
            "type": "leaf",
            "state": {
              "type": "outline",
              "state": {
                "file": "欢迎.md",
                "followCursor": false,
                "showSearch": false,
                "searchQuery": ""
              },
              "icon": "lucide-list",
              "title": "欢迎 的大纲"
            }
          },
          {
            "id": "1084dbbfde9b1c9a",
            "type": "leaf",
            "state": {
              "type": "git-view",
              "state": {},
              "icon": "git-pull-request",
              "title": "Source Control"
            }
          }
        ],
        "currentTab": 5
      }
    ],
    "direction": "horizontal",
    "width": 300
  },
  "left-ribbon": {
    "hiddenItems": {
      "switcher:打开快速切换": false,
      "graph:查看关系图谱": false,
      "canvas:新建白板": false,
      "daily-notes:打开/创建今天的日记": false,
      "templates:插入模板": false,
      "command-palette:打开命令面板": false,
      "bases:创建新数据库": false,
      "obsidian-git:Open Git source control": false
    }
  },
  "active": "1084dbbfde9b1c9a",
  "lastOpenFiles": [
    "代码随想录-算法训练营/day39_动态规划_part07/【动态规划】打家劫舍 II.md",
    "代码随想录-算法训练营/day39_动态规划_part07/【动态规划】【树上dp】打家劫舍 III.md",
    "代码随想录-算法训练营/day39_动态规划_part07/【动态规划】打家劫舍.md",
    "代码随想录-算法训练营/day38_动态规划_part06/【动态规划】【完全背包】单词拆分.md",
    "代码随想录-算法训练营/day39_动态规划_part07",
    "代码随想录-算法训练营/day38_动态规划_part06/【动态规划】【完全背包】完全平方数.md",
    "代码随想录-算法训练营/day38_动态规划_part06/【动态规划】【完全背包】零钱兑换.md",
    "代码随想录-算法训练营/day37_动态规划_part05/【动态规划】【完全背包】爬楼梯.md",
    "代码随想录-算法训练营/day38_动态规划_part06",
    "代码随想录-算法训练营/day37_动态规划_part05/【动态规划】组合总和 Ⅳ.md",
    "代码随想录-算法训练营/day37_动态规划_part05/【动态规划】【完全背包】零钱兑换 II.md",
    "代码随想录-算法训练营/day37_动态规划_part05/【动态规划】完全背包问题.md",
    "代码随想录-算法训练营/day36_动态规划_part04/【动态规划】【01背包】最后一块石头的重量 II.md",
    "代码随想录-算法训练营/day36_动态规划_part04/【动态规划】【二维DP】一和零.md",
    "代码随想录-算法训练营/day37_动态规划_part05",
    "代码随想录-算法训练营/day36_动态规划_part04/【动态规划】【01背包】目标和.md",
    "代码随想录-算法训练营/day35_动态规划_part03/【动态规划】【01背包】分割等和子集.md",
    "代码随想录-算法训练营/day36_动态规划_part04",
    "代码随想录-算法训练营/day35_动态规划_part03/【动态规划】01 背包问题（一维 DP - 滚动数组）.md",
    "代码随想录-算法训练营/day35_动态规划_part03/【动态规划】01 背包问题（二维 DP）.md",
    "代码随想录-算法训练营/day34_动态规划_part02/【动态规划】不同的二叉搜索树.md",
    "代码随想录-算法训练营/day35_动态规划_part03",
    "代码随想录-算法训练营/day34_动态规划_part02/【动态规划】整数拆分.md",
    "代码随想录-算法训练营/day34_动态规划_part02/【动态规划】不同路径 II.md",
    "代码随想录-算法训练营/day34_动态规划_part02/【动态规划】不同路径.md",
    "代码随想录-算法训练营/day32_贪心_part05/【贪心】监控二叉树.md",
    "代码随想录-算法训练营/day34_动态规划_part02",
    "代码随想录-算法训练营/day32_贪心_part05/【贪心】划分字母区间.md",
    "代码随想录-算法训练营/day32_贪心_part05/【贪心】单调递增的数字.md",
    "代码随想录-算法训练营/day31_贪心_part04/【贪心】用最少数量的箭引爆.md",
    "代码随想录-算法训练营/day31_贪心_part04/【贪心】无重叠区间.md",
    "代码随想录-算法训练营/day31_贪心_part04/【贪心】划分字母区间.md",
    "代码随想录-算法训练营/day33_动态规划_part01",
    "代码随想录-算法训练营/day32_贪心_part05",
    "代码随想录-算法训练营/day31_贪心_part04",
    "代码随想录-算法训练营/day29_贪心_part03",
    "cod僵尸彩蛋流程随手记/cod22第一赛季-浩劫灾星/图片/c4火力全开.png",
    "cod僵尸彩蛋流程随手记/cod22第一赛季-浩劫灾星/图片/c4一击必杀.png",
    "cod僵尸彩蛋流程随手记/cod22第一赛季-浩劫灾星/图片/阅读清单.png",
    "cod僵尸彩蛋流程随手记/cod22第一赛季-浩劫灾星/图片/骨锯.png",
    "cod僵尸彩蛋流程随手记/cod22第一赛季-浩劫灾星/图片/大脑坚守.png",
    "cod僵尸彩蛋流程随手记/cod22第一赛季-浩劫灾星/图片/符号1.png",
    "cod僵尸彩蛋流程随手记/cod22第一赛季-浩劫灾星/图片/符号5.png",
    "cod僵尸彩蛋流程随手记/cod22第一赛季-浩劫灾星/图片/符号4.png",
    "cod僵尸彩蛋流程随手记/cod22第一赛季-浩劫灾星/图片/符号3.png",
    "cod僵尸彩蛋流程随手记/cod22第一赛季-浩劫灾星/图片/符号2.png",
    "未命名.canvas"
  ]
}